[{"Etunimi":"Saara","Voitot":2,"Tappiot":1,"Tasapelit":0},{"Etunimi":"Emilia","Voitot":0,"Tappiot":1,"Tasapelit":0},{"Etunimi":"Jukkis","Voitot":1,"Tappiot":2,"Tasapelit":0},{"Etunimi":"Timo","Voitot":1,"Tappiot":2,"Tasapelit":0},{"Etunimi":"Kalle","Voitot":1,"Tappiot":1,"Tasapelit":0},{"Etunimi":"Jussi","Voitot":0,"Tappiot":1,"Tasapelit":0},{"Etunimi":"Pekka","Voitot":0,"Tappiot":1,"Tasapelit":0},{"Etunimi":"Pentti","Voitot":0,"Tappiot":1,"Tasapelit":0},{"Etunimi":"Juuli","Voitot":1,"Tappiot":2,"Tasapelit":0},{"Etunimi":"Justus","Voitot":1,"Tappiot":1,"Tasapelit":0},{"Etunimi":"Tiina","Voitot":1,"Tappiot":1,"Tasapelit":0},{"Etunimi":"Paavi","Voitot":1,"Tappiot":1,"Tasapelit":0},{"Etunimi":"Marjukka","Voitot":0,"Tappiot":2,"Tasapelit":0},{"Etunimi":"Jeesus","Voitot":0,"Tappiot":4,"Tasapelit":0},{"Etunimi":"Salla","Voitot":1,"Tappiot":0,"Tasapelit":0}]